pdk_client/__init__.py
pdk_client/client.py
passive_data_kit_client-0.1.0.dist-info/LICENSE
passive_data_kit_client-0.1.0.dist-info/METADATA
passive_data_kit_client-0.1.0.dist-info/WHEEL
passive_data_kit_client-0.1.0.dist-info/top_level.txt
passive_data_kit_client-0.1.0.dist-info/RECORD
