Metadata-Version: 2.1
Name: passive-data-kit-client
Version: 0.1.0
Summary: Client library for interacting with Passive Data Kit servers
Home-page: https://github.com/audaciouscode/PassiveDataKit-Client-Python
Author: Chris J. Karr
Author-email: chris@audacious-software.com
License: Apache License
Requires-Dist: arrow (==0.13.0)
Requires-Dist: backports.functools-lru-cache (==1.5)
Requires-Dist: certifi (==2018.11.29)
Requires-Dist: chardet (==3.0.4)
Requires-Dist: idna (==2.8)
Requires-Dist: python-dateutil (==2.8.0)
Requires-Dist: requests (==2.21.0)
Requires-Dist: six (==1.12.0)
Requires-Dist: urllib3 (==1.24.1)
